Metadata-Version: 2.1
Name: airflow_dbt
Version: 0.4.0
Summary: Apache Airflow integration for dbt
Home-page: https://github.com/gocardless/airflow-dbt
Author: GoCardless
Author-email: engineering@gocardless.com
License: MIT
Platform: UNKNOWN
Classifier: Development Status :: 5 - Production/Stable
Classifier: License :: OSI Approved :: MIT License
Classifier: Operating System :: MacOS :: MacOS X
Classifier: Operating System :: POSIX :: Linux
Classifier: Programming Language :: Python :: 3.7
License-File: LICENSE.txt
